daveagent_cli-1.0.9.dist-info/licenses/LICENSE
src/__init__.py
src/cli.py
src/main.py
src/config/__init__.py
src/config/constants.py
src/config/prompts.py
src/config/settings.py
src/interfaces/__init__.py
src/interfaces/cli_interface.py
src/managers/__init__.py
src/managers/context_manager.py
src/managers/error_reporter.py
src/managers/rag_manager.py
src/managers/state_manager.py
src/observability/__init__.py
src/observability/langfuse_simple.py
src/skills/__init__.py
src/skills/manager.py
src/skills/models.py
src/skills/parser.py
src/tools/__init__.py
src/tools/code_analyzer.py
src/tools/code_analyzer_test.py
src/tools/common.py
src/tools/csv_tools.py
src/tools/delete_file.py
src/tools/delete_file_test.py
src/tools/directory_ops.py
src/tools/directory_ops_test.py
src/tools/edit_file.py
src/tools/edit_file_test.py
src/tools/git_operations.py
src/tools/glob.py
src/tools/glob_test.py
src/tools/grep.py
src/tools/grep_test.py
src/tools/json_tools.py
src/tools/json_tools_test.py
src/tools/read_file.py
src/tools/read_file_test.py
src/tools/request_plan_approval.py
src/tools/search_file.py
src/tools/search_file_test.py
src/tools/terminal.py
src/tools/terminal_test.py
src/tools/web_search.py
src/tools/wikipedia_tools.py
src/tools/write_file.py
src/tools/write_file_test.py
src/utils/__init__.py
src/utils/conversation_tracker.py
src/utils/deepseek_fix.py
src/utils/deepseek_reasoning_client.py
src/utils/errors.py
src/utils/file_indexer.py
src/utils/file_selector.py
src/utils/file_utils.py
src/utils/history_viewer.py
src/utils/interaction.py
src/utils/json_logger.py
src/utils/language_detection.py
src/utils/linter.py
src/utils/llm_edit_fixer.py
src/utils/logger.py
src/utils/logging_model_client.py
src/utils/model_settings.py
src/utils/permissions.py
src/utils/setup_wizard.py
src/utils/vibe_spinner.py
daveagent_cli-1.0.9.dist-info/METADATA
daveagent_cli-1.0.9.dist-info/WHEEL
daveagent_cli-1.0.9.dist-info/entry_points.txt
daveagent_cli-1.0.9.dist-info/top_level.txt
daveagent_cli-1.0.9.dist-info/RECORD
