Metadata-Version: 2.4
Name: daveagent-cli
Version: 1.0.9
Summary: AI-powered coding assistant with intelligent agent orchestration
Home-page: https://github.com/davidmonterocrespo24/DaveAgent
Author: DaveAgent Team
Author-email: DaveAgent Team <davidmonterocrespo24@gmail.com>
License: MIT
Project-URL: Homepage, https://github.com/davidmonterocrespo24/DaveAgent
Project-URL: Documentation, https://daveagent.readthedocs.io
Project-URL: Repository, https://github.com/davidmonterocrespo24/DaveAgent
Project-URL: Bug Tracker, https://github.com/davidmonterocrespo24/DaveAgent/issues
Keywords: ai,agent,coding,assistant,llm,autogen
Classifier: Development Status :: 4 - Beta
Classifier: Intended Audience :: Developers
Classifier: Topic :: Software Development :: Libraries :: Application Frameworks
Classifier: License :: OSI Approved :: MIT License
Classifier: Programming Language :: Python :: 3
Classifier: Programming Language :: Python :: 3.10
Classifier: Programming Language :: Python :: 3.11
Classifier: Programming Language :: Python :: 3.12
Requires-Python: >=3.10
License-File: LICENSE
Requires-Dist: autogen-agentchat>=0.7.5
Requires-Dist: autogen-ext[openai]>=0.7.5
Requires-Dist: prompt-toolkit>=3.0.0
Requires-Dist: rich>=13.0.0
Requires-Dist: readchar>=4.0.0
Requires-Dist: pandas>=2.0.0
Requires-Dist: wikipedia>=1.4.0
Requires-Dist: python-dotenv>=1.0.0
Requires-Dist: tiktoken>=0.5.0
Provides-Extra: dev
Requires-Dist: pytest>=7.0.0; extra == "dev"
Requires-Dist: pytest-asyncio>=0.21.0; extra == "dev"
Requires-Dist: pytest-cov>=4.0.0; extra == "dev"
Requires-Dist: ruff>=0.8.0; extra == "dev"
Requires-Dist: mypy>=1.0.0; extra == "dev"
Dynamic: author
Dynamic: home-page
Dynamic: license-file
Dynamic: requires-python
